landsatxplore/__init__.py
landsatxplore/api.py
landsatxplore/cli.py
landsatxplore/earthexplorer.py
landsatxplore/errors.py
landsatxplore/util.py
landsatxplore-0.15.0.dist-info/LICENSE.txt
landsatxplore-0.15.0.dist-info/METADATA
landsatxplore-0.15.0.dist-info/WHEEL
landsatxplore-0.15.0.dist-info/entry_points.txt
landsatxplore-0.15.0.dist-info/RECORD
