Metadata-Version: 2.1
Name: landsatxplore
Version: 0.15.0
Summary: Search and download Landsat scenes from EarthExplorer
Home-page: https://github.com/yannforget/landsatxplore
License: MIT
Keywords: earth observation,remote sesing,GIS,satellite imagery,landsat,sentinel,usgs
Author: Yann Forget
Author-email: yannforget@mailbox.org
Maintainer: Yann Forget
Maintainer-email: yannforget@mailbox.org
Requires-Python: >=3.7,<4.0
Classifier: License :: OSI Approved :: MIT License
Classifier: Programming Language :: Python :: 3
Classifier: Programming Language :: Python :: 3.7
Classifier: Programming Language :: Python :: 3.8
Classifier: Programming Language :: Python :: 3.9
Classifier: Programming Language :: Python :: 3.10
Classifier: Programming Language :: Python :: 3.11
Requires-Dist: click (>=7.1,<8.0)
Requires-Dist: python-dateutil (>=2.8,<3.0)
Requires-Dist: requests (>=2.20,<3.0)
Requires-Dist: shapely (>=1.7,<2.0)
Requires-Dist: tqdm (>=4.58,<5.0)
Project-URL: Documentation, https://github.com/yannforget/landsatxplore
Project-URL: Repository, https://github.com/yannforget/landsatxplore
Project-URL: issues, https://github.com/yannforget/landsatxplore/issues
